{"level":"A1","sublevel":"2","full_level":"A1.2","name":"A1.2 — Начальный уровень (часть 2)","name_de":"A1.2 — Anfänger (Teil 2)","description":"Вторая часть базового уровня: контент уровня A2 по стандартам Goethe-Institut","version":"1.0.0","last_updated":"2026-03-01","content":{"vocabulary":{"path":"vocabulary/","categories":[{"id":"personal","file":"personal.json","name":"Личная информация"},{"id":"family","file":"family.json","name":"Семья"},{"id":"food","file":"food.json","name":"Еда и напитки"},{"id":"home","file":"home.json","name":"Дом и жильё"},{"id":"time","file":"time.json","name":"Время"},{"id":"verbs","file":"verbs.json","name":"Важные глаголы"},{"id":"transport","file":"transport.json","name":"Транспорт и город"},{"id":"shopping","file":"shopping.json","name":"Покупки"},{"id":"numbers","file":"numbers.json","name":"Числа"},{"id":"adjectives","file":"adjectives.json","name":"Прилагательные"},{"id":"phrases","file":"phrases.json","name":"Важные фразы"}],"total_words":1155},"grammar":{"path":"grammar/","topics":[{"id":"articles","file":"articles.json","name":"Артикли (der, die, das)"},{"id":"sein_haben","file":"sein_haben.json","name":"Глаголы sein и haben"},{"id":"present_tense","file":"present_tense.json","name":"Настоящее и прошедшее время"},{"id":"negation","file":"negation.json","name":"Отрицание (nicht / kein)"},{"id":"word_order","file":"word_order.json","name":"Порядок слов и придаточные"},{"id":"akkusativ","file":"akkusativ.json","name":"Датив (Dativ)"},{"id":"modal_verbs","file":"modal_verbs.json","name":"Модальные глаголы"},{"id":"questions","file":"questions.json","name":"Вопросительные слова"}],"total_questions":142},"phrases":{"path":"phrases/","categories":[{"id":"apartment","file":"apartment.json","name":"Квартира"},{"id":"bank","file":"bank.json","name":"В банке"},{"id":"cafe","file":"cafe.json","name":"В кафе"},{"id":"clothes","file":"clothes.json","name":"Одежда"},{"id":"directions","file":"directions.json","name":"Направления"},{"id":"doctor","file":"doctor.json","name":"У врача"},{"id":"family","file":"family.json","name":"Семья"},{"id":"food","file":"food.json","name":"Еда"},{"id":"free_time","file":"free_time.json","name":"Свободное время"},{"id":"home","file":"home.json","name":"Дом"},{"id":"hotel","file":"hotel.json","name":"В отеле"},{"id":"neighbors","file":"neighbors.json","name":"Соседи"},{"id":"post_office","file":"post_office.json","name":"На почте"},{"id":"school","file":"school.json","name":"Школа"},{"id":"shop","file":"shop.json","name":"В магазине"},{"id":"station","file":"station.json","name":"На вокзале"},{"id":"transport","file":"transport.json","name":"Транспорт"},{"id":"travel","file":"travel.json","name":"Путешествия"},{"id":"weather","file":"weather.json","name":"Погода"},{"id":"work","file":"work.json","name":"Работа"}],"total_phrases":2015,"status":"active"},"dialogues":{"path":"dialogues/","topics":[{"id":"apartment","file":"apartment.json","name":"Квартира"},{"id":"bank","file":"bank.json","name":"В банке"},{"id":"cafe","file":"cafe.json","name":"В кафе"},{"id":"clothes","file":"clothes.json","name":"Одежда"},{"id":"directions","file":"directions.json","name":"Направления"},{"id":"doctor","file":"doctor.json","name":"У врача"},{"id":"family","file":"family.json","name":"Семья"},{"id":"free_time","file":"free_time.json","name":"Свободное время"},{"id":"greetings","file":"greetings.json","name":"Приветствия"},{"id":"home","file":"home.json","name":"Дом"},{"id":"hotel","file":"hotel.json","name":"В отеле"},{"id":"neighbors","file":"neighbors.json","name":"Соседи"},{"id":"post_office","file":"post_office.json","name":"На почте"},{"id":"restaurant","file":"restaurant.json","name":"В ресторане"},{"id":"school","file":"school.json","name":"Школа"},{"id":"shop","file":"shop.json","name":"В магазине"},{"id":"station","file":"station.json","name":"На вокзале"},{"id":"travel","file":"travel.json","name":"Путешествие"},{"id":"weather","file":"weather.json","name":"Погода"},{"id":"work","file":"work.json","name":"Работа"}],"total_dialogues":20,"status":"active"},"exercises":{"path":"exercises/","types":[],"status":"planned"},"culture":{"path":"culture/","topics":[],"status":"planned"}},"exam_info":{"name":"Goethe-Zertifikat A2","parts":[{"name":"Hören","description":"Аудирование","duration":"30 минут"},{"name":"Lesen","description":"Чтение","duration":"30 минут"},{"name":"Schreiben","description":"Письмо","duration":"30 минут"},{"name":"Sprechen","description":"Говорение","duration":"15 минут"}],"passing_score":"60%"}}
